XStatic_Angular_Vis-4.16.0.0-py2.7-nspkg.pth
XStatic_Angular_Vis-4.16.0.0.dist-info/METADATA
XStatic_Angular_Vis-4.16.0.0.dist-info/RECORD
XStatic_Angular_Vis-4.16.0.0.dist-info/WHEEL
XStatic_Angular_Vis-4.16.0.0.dist-info/namespace_packages.txt
XStatic_Angular_Vis-4.16.0.0.dist-info/top_level.txt
xstatic/pkg/angular_vis/__init__.py
xstatic/pkg/angular_vis/data/angular-vis.js
