Metadata-Version: 2.1
Name: XStatic-Angular-Vis
Version: 4.16.0.0
Summary: Angular-Vis 4.16.0 (XStatic packaging standard)
Home-page: https://github.com/visjs/angular-visjs
Maintainer: xinni.ge
Maintainer-email: xinni.ge@ntt.com
License: MIT
Keywords: angular_vis xstatic
Platform: any
